<?xml version="1.0" encoding="UTF-8"?>
<!DOCTYPE nmaprun>
<?xml-stylesheet href="file:///usr/bin/../share/nmap/nmap.xsl" type="text/xsl"?>
<!-- Nmap 7.80 scan initiated Thu Dec 15 23:17:20 2022 as: nmap -sV -iL ports/5473.txt -p 5473 -oX outputs/nmapOutput-5473.xml -->
<nmaprun scanner="nmap" args="nmap -sV -iL ports/5473.txt -p 5473 -oX outputs/nmapOutput-5473.xml" start="1671146240" startstr="Thu Dec 15 23:17:20 2022" version="7.80" xmloutputversion="1.04">
<scaninfo type="connect" protocol="tcp" numservices="1" services="5473"/>
<verbose level="0"/>
<debugging level="0"/>
<host starttime="1671146240" endtime="1671146259"><status state="up" reason="conn-refused" reason_ttl="0"/>
<address addr="212.33.134.46" addrtype="ipv4"/>
<hostnames>
<hostname name="46.212-33-134.static.xfiber.net" type="PTR"/>
</hostnames>
<ports><port protocol="tcp" portid="5473"><state state="open" reason="syn-ack" reason_ttl="0"/><service name="apsolab-tags" method="table" conf="3"/></port>
</ports>
<times srtt="28167" rttvar="21138" to="112719"/>
</host>
<host starttime="1671146240" endtime="1671146259"><status state="up" reason="conn-refused" reason_ttl="0"/>
<address addr="212.33.134.46" addrtype="ipv4"/>
<hostnames>
<hostname name="46.212-33-134.static.xfiber.net" type="PTR"/>
</hostnames>
<ports><port protocol="tcp" portid="5473"><state state="open" reason="syn-ack" reason_ttl="0"/><service name="apsolab-tags" method="table" conf="3"/></port>
</ports>
<times srtt="28016" rttvar="21064" to="112272"/>
</host>
<host starttime="1671146240" endtime="1671146259"><status state="up" reason="conn-refused" reason_ttl="0"/>
<address addr="212.33.134.46" addrtype="ipv4"/>
<hostnames>
<hostname name="46.212-33-134.static.xfiber.net" type="PTR"/>
</hostnames>
<ports><port protocol="tcp" portid="5473"><state state="open" reason="syn-ack" reason_ttl="0"/><service name="apsolab-tags" method="table" conf="3"/></port>
</ports>
<times srtt="27865" rttvar="20901" to="111469"/>
</host>
<host starttime="1671146240" endtime="1671146260"><status state="up" reason="conn-refused" reason_ttl="0"/>
<address addr="212.33.134.46" addrtype="ipv4"/>
<hostnames>
<hostname name="46.212-33-134.static.xfiber.net" type="PTR"/>
</hostnames>
<ports><port protocol="tcp" portid="5473"><state state="open" reason="syn-ack" reason_ttl="0"/><service name="apsolab-tags" method="table" conf="3"/></port>
</ports>
<times srtt="28188" rttvar="21143" to="112760"/>
</host>
<runstats><finished time="1671146260" timestr="Thu Dec 15 23:17:40 2022" elapsed="19.89" summary="Nmap done at Thu Dec 15 23:17:40 2022; 4 IP addresses (4 hosts up) scanned in 19.89 seconds" exit="success"/><hosts up="4" down="0" total="4"/>
</runstats>
</nmaprun>
